beep_utils/__init__.py
beep_utils/beep_utils.py
beep_utils-0.0.5.dist-info/METADATA
beep_utils-0.0.5.dist-info/WHEEL
beep_utils-0.0.5.dist-info/top_level.txt
beep_utils-0.0.5.dist-info/RECORD
