Metadata-Version: 2.1
Name: beep-utils
Version: 0.0.5
Summary: Beep Saúde 
Home-page: UNKNOWN
Author: Lucas Pinho
License: UNKNOWN
Platform: UNKNOWN
Classifier: Programming Language :: Python :: 3
Classifier: License :: OSI Approved :: MIT License
Classifier: Operating System :: OS Independent
Requires-Python: >=3.8
